EcoMod.py
ecomod-0.1.6.dist-info/LICENSE
ecomod-0.1.6.dist-info/WHEEL
ecomod-0.1.6.dist-info/METADATA
ecomod-0.1.6.dist-info/RECORD
