Metadata-Version: 2.1
Name: EcoMod
Version: 0.1.6
Summary: A simple species distribution modelling package. Functionality is currently limited to BIOCLIM.
Keywords: species distribution,ecological niche,habitat suitability
Author-email: Wen Kang Lee <wynn.wk.lee@gmail.com>
Requires-Python: >=3.11
Classifier: Programming Language :: Python :: 3
Classifier: License :: OSI Approved :: MIT License
Classifier: Operating System :: OS Independent
Classifier: Development Status :: 4 - Beta
Classifier: Intended Audience :: Science/Research
Classifier: Topic :: Scientific/Engineering :: GIS
Requires-Dist: pygbif
Requires-Dist: numpy
Requires-Dist: matplotlib
Requires-Dist: scikit-learn
Project-URL: Documentation, https://flit.pypa.io
Project-URL: Source, https://github.com/WenKang-Lee/EcoMod
